MANIFEST.in
README.md
setup.py
ctmc/__init__.py
ctmc/aggregateevents.py
ctmc/ctmc_class.py
ctmc/ctmc_func.py
ctmc/datacheck.py
ctmc/datacorrection.py
ctmc/errorcheck.py
ctmc/generatormatrix.py
ctmc/simulate.py
ctmc.egg-info/PKG-INFO
ctmc.egg-info/SOURCES.txt
ctmc.egg-info/dependency_links.txt
ctmc.egg-info/not-zip-safe
ctmc.egg-info/requires.txt
ctmc.egg-info/top_level.txt
test/__init__.py
test/test_aggregateevents.py
test/test_datacheck.py
test/test_datacorrection.py
test/test_errorcheck.py