Metadata-Version: 2.1
Name: ctmc
Version: 0.1.3
Summary: Continous Time Markov Chain
Home-page: http://github.com/kmedian/ctmc
Author: Ulf Hamster
Author-email: 554c46@gmail.com
License: MIT
Platform: UNKNOWN
Requires-Python: >=3.6
